conda/warpkit-conda-install.sh
conda/meta.yaml
include/romeo.h
include/utilities.h
include/warps.h
include/itk/itkModifiedInvertDisplacementFieldImageFilter.h
include/itk/itkModifiedInvertDisplacementFieldImageFilter.hxx
tests/data/download_bids_testdata.sh
notes/fmap.png
notes/phase.png
cmake_aux/FindJulia.cmake
warpkit/distortion.py
warpkit/warpkit_cpp.cpython-38-darwin.so
warpkit/concurrency.py
warpkit/__init__.py
warpkit/unwrap.py
warpkit/model.py
warpkit/utilities.py
warpkit/julia.py
warpkit/scripts/extract_field_from_maps.py
warpkit/scripts/__init__.py
warpkit/scripts/medic.py
warpkit/share/doc/ITK-5.4/LICENSE
warpkit/share/doc/ITK-5.4/NOTICE
warpkit/share/doc/ITK-5.4/README.md
warpkit/share/doc/ITK-5.4/itksys/Copyright.txt
warpkit-0.1.1.dist-info/zip-safe
warpkit-0.1.1.dist-info/RECORD
warpkit-0.1.1.dist-info/LICENSE
warpkit-0.1.1.dist-info/WHEEL
warpkit-0.1.1.dist-info/entry_points.txt
warpkit-0.1.1.dist-info/top_level.txt
warpkit-0.1.1.dist-info/METADATA
src/warpkit.cpp
