Metadata-Version: 2.1
Name: warpkit
Version: 0.1.1
Summary: A python library for neuroimaging transformations
Author-email: Andrew Van <vanandrew@wustl.edu>
Project-URL: github, https://github.com/vanandrew/warpkit
Keywords: neuroimaging
Classifier: Programming Language :: Python :: 3
Requires-Python: >=3.8
License-File: LICENSE
Requires-Dist: nibabel >=4.0.2
Requires-Dist: numpy >=1.23.3
Requires-Dist: scikit-image >=0.20.0
Requires-Dist: scipy >=1.8.1
Requires-Dist: transforms3d >=0.4.1
Requires-Dist: indexed-gzip >=1.7.0
Provides-Extra: dev
Requires-Dist: black >=22.3.0 ; extra == 'dev'
Requires-Dist: coverage[toml] >=5.5 ; extra == 'dev'
Requires-Dist: pytest >=7.2.2 ; extra == 'dev'
Requires-Dist: pytest-pycodestyle >=2.2.0 ; extra == 'dev'
Requires-Dist: pybids >=0.15.1 ; extra == 'dev'
